{"entries":[{"name":"100 Continue","path":"status/100","type":"Status","url":"/en-US/docs/Web/HTTP/Status/100"},{"name":"100 Continue (RFC 7231)","path":"rfc7231#section-6.2.1","type":"Status","url":"/doc/html/rfc7231#section-6.2.1"},{"name":"101 Switching Protocols","path":"status/101","type":"Status","url":"/en-US/docs/Web/HTTP/Status/101"},{"name":"101 Switching Protocols (RFC 7231)","path":"rfc7231#section-6.2.2","type":"Status","url":"/doc/html/rfc7231#section-6.2.2"},{"name":"103 Early Hints","path":"status/103","type":"Status","url":"/en-US/docs/Web/HTTP/Status/103"},{"name":"200 OK","path":"status/200","type":"Status","url":"/en-US/docs/Web/HTTP/Status/200"},{"name":"200 OK (RFC 7231)","path":"rfc7231#section-6.3.1","type":"Status","url":"/doc/html/rfc7231#section-6.3.1"},{"name":"201 Created","path":"status/201","type":"Status","url":"/en-US/docs/Web/HTTP/Status/201"},{"name":"201 Created (RFC 7231)","path":"rfc7231#section-6.3.2","type":"Status","url":"/doc/html/rfc7231#section-6.3.2"},{"name":"202 Accepted","path":"status/202","type":"Status","url":"/en-US/docs/Web/HTTP/Status/202"},{"name":"202 Accepted (RFC 7231)","path":"rfc7231#section-6.3.3","type":"Status","url":"/doc/html/rfc7231#section-6.3.3"},{"name":"203 Non-Authoritative Information","path":"status/203","type":"Status","url":"/en-US/docs/Web/HTTP/Status/203"},{"name":"203 Non-Authoritative Information (RFC 7231)","path":"rfc7231#section-6.3.4","type":"Status","url":"/doc/html/rfc7231#section-6.3.4"},{"name":"204 No Content","path":"status/204","type":"Status","url":"/en-US/docs/Web/HTTP/Status/204"},{"name":"204 No Content (RFC 7231)","path":"rfc7231#section-6.3.5","type":"Status","url":"/doc/html/rfc7231#section-6.3.5"},{"name":"205 Reset Content","path":"status/205","type":"Status","url":"/en-US/docs/Web/HTTP/Status/205"},{"name":"205 Reset Content (RFC 7231)","path":"rfc7231#section-6.3.6","type":"Status","url":"/doc/html/rfc7231#section-6.3.6"},{"name":"206 Partial Content","path":"status/206","type":"Status","url":"/en-US/docs/Web/HTTP/Status/206"},{"name":"207 Multi-Status (RFC 4918)","path":"rfc4918#section-11.1","type":"Status","url":"/doc/html/rfc4918#section-11.1"},{"name":"300 Multiple Choices","path":"status/300","type":"Status","url":"/en-US/docs/Web/HTTP/Status/300"},{"name":"300 Multiple Choices (RFC 7231)","path":"rfc7231#section-6.4.1","type":"Status","url":"/doc/html/rfc7231#section-6.4.1"},{"name":"301 Moved Permanently","path":"status/301","type":"Status","url":"/en-US/docs/Web/HTTP/Status/301"},{"name":"301 Moved Permanently (RFC 7231)","path":"rfc7231#section-6.4.2","type":"Status","url":"/doc/html/rfc7231#section-6.4.2"},{"name":"302 Found","path":"status/302","type":"Status","url":"/en-US/docs/Web/HTTP/Status/302"},{"name":"302 Found (RFC 7231)","path":"rfc7231#section-6.4.3","type":"Status","url":"/doc/html/rfc7231#section-6.4.3"},{"name":"303 See Other","path":"status/303","type":"Status","url":"/en-US/docs/Web/HTTP/Status/303"},{"name":"303 See Other (RFC 7231)","path":"rfc7231#section-6.4.4","type":"Status","url":"/doc/html/rfc7231#section-6.4.4"},{"name":"304 Not Modified","path":"status/304","type":"Status","url":"/en-US/docs/Web/HTTP/Status/304"},{"name":"305 Use Proxy (RFC 7231)","path":"rfc7231#section-6.4.5","type":"Status","url":"/doc/html/rfc7231#section-6.4.5"},{"name":"306 (Unused) (RFC 7231)","path":"rfc7231#section-6.4.6","type":"Status","url":"/doc/html/rfc7231#section-6.4.6"},{"name":"307 Temporary Redirect","path":"status/307","type":"Status","url":"/en-US/docs/Web/HTTP/Status/307"},{"name":"307 Temporary Redirect (RFC 7231)","path":"rfc7231#section-6.4.7","type":"Status","url":"/doc/html/rfc7231#section-6.4.7"},{"name":"308 Permanent Redirect","path":"status/308","type":"Status","url":"/en-US/docs/Web/HTTP/Status/308"},{"name":"400 Bad Request","path":"status/400","type":"Status","url":"/en-US/docs/Web/HTTP/Status/400"},{"name":"400 Bad Request (RFC 7231)","path":"rfc7231#section-6.5.1","type":"Status","url":"/doc/html/rfc7231#section-6.5.1"},{"name":"401 Unauthorized","path":"status/401","type":"Status","url":"/en-US/docs/Web/HTTP/Status/401"},{"name":"402 Payment Required","path":"status/402","type":"Status","url":"/en-US/docs/Web/HTTP/Status/402"},{"name":"402 Payment Required (RFC 7231)","path":"rfc7231#section-6.5.2","type":"Status","url":"/doc/html/rfc7231#section-6.5.2"},{"name":"403 Forbidden","path":"status/403","type":"Status","url":"/en-US/docs/Web/HTTP/Status/403"},{"name":"403 Forbidden (RFC 7231)","path":"rfc7231#section-6.5.3","type":"Status","url":"/doc/html/rfc7231#section-6.5.3"},{"name":"404 Not Found","path":"status/404","type":"Status","url":"/en-US/docs/Web/HTTP/Status/404"},{"name":"404 Not Found (RFC 7231)","path":"rfc7231#section-6.5.4","type":"Status","url":"/doc/html/rfc7231#section-6.5.4"},{"name":"405 Method Not Allowed","path":"status/405","type":"Status","url":"/en-US/docs/Web/HTTP/Status/405"},{"name":"405 Method Not Allowed (RFC 7231)","path":"rfc7231#section-6.5.5","type":"Status","url":"/doc/html/rfc7231#section-6.5.5"},{"name":"406 Not Acceptable","path":"status/406","type":"Status","url":"/en-US/docs/Web/HTTP/Status/406"},{"name":"406 Not Acceptable (RFC 7231)","path":"rfc7231#section-6.5.6","type":"Status","url":"/doc/html/rfc7231#section-6.5.6"},{"name":"407 Proxy Authentication Required","path":"status/407","type":"Status","url":"/en-US/docs/Web/HTTP/Status/407"},{"name":"408 Request Timeout","path":"status/408","type":"Status","url":"/en-US/docs/Web/HTTP/Status/408"},{"name":"408 Request Timeout (RFC 7231)","path":"rfc7231#section-6.5.7","type":"Status","url":"/doc/html/rfc7231#section-6.5.7"},{"name":"409 Conflict","path":"status/409","type":"Status","url":"/en-US/docs/Web/HTTP/Status/409"},{"name":"409 Conflict (RFC 7231)","path":"rfc7231#section-6.5.8","type":"Status","url":"/doc/html/rfc7231#section-6.5.8"},{"name":"410 Gone","path":"status/410","type":"Status","url":"/en-US/docs/Web/HTTP/Status/410"},{"name":"410 Gone (RFC 7231)","path":"rfc7231#section-6.5.9","type":"Status","url":"/doc/html/rfc7231#section-6.5.9"},{"name":"411 Length Required","path":"status/411","type":"Status","url":"/en-US/docs/Web/HTTP/Status/411"},{"name":"411 Length Required (RFC 7231)","path":"rfc7231#section-6.5.10","type":"Status","url":"/doc/html/rfc7231#section-6.5.10"},{"name":"412 Precondition Failed","path":"status/412","type":"Status","url":"/en-US/docs/Web/HTTP/Status/412"},{"name":"413 Payload Too Large","path":"status/413","type":"Status","url":"/en-US/docs/Web/HTTP/Status/413"},{"name":"413 Payload Too Large (RFC 7231)","path":"rfc7231#section-6.5.11","type":"Status","url":"/doc/html/rfc7231#section-6.5.11"},{"name":"414 URI Too Long","path":"status/414","type":"Status","url":"/en-US/docs/Web/HTTP/Status/414"},{"name":"414 URI Too Long (RFC 7231)","path":"rfc7231#section-6.5.12","type":"Status","url":"/doc/html/rfc7231#section-6.5.12"},{"name":"415 Unsupported Media Type","path":"status/415","type":"Status","url":"/en-US/docs/Web/HTTP/Status/415"},{"name":"415 Unsupported Media Type (RFC 7231)","path":"rfc7231#section-6.5.13","type":"Status","url":"/doc/html/rfc7231#section-6.5.13"},{"name":"416 Range Not Satisfiable","path":"status/416","type":"Status","url":"/en-US/docs/Web/HTTP/Status/416"},{"name":"417 Expectation Failed","path":"status/417","type":"Status","url":"/en-US/docs/Web/HTTP/Status/417"},{"name":"417 Expectation Failed (RFC 7231)","path":"rfc7231#section-6.5.14","type":"Status","url":"/doc/html/rfc7231#section-6.5.14"},{"name":"418 I'm a teapot","path":"status/418","type":"Status","url":"/en-US/docs/Web/HTTP/Status/418"},{"name":"422 Unprocessable Entity","path":"status/422","type":"Status","url":"/en-US/docs/Web/HTTP/Status/422"},{"name":"422 Unprocessable Entity (RFC 4918)","path":"rfc4918#section-11.2","type":"Status","url":"/doc/html/rfc4918#section-11.2"},{"name":"423 Locked (RFC 4918)","path":"rfc4918#section-11.3","type":"Status","url":"/doc/html/rfc4918#section-11.3"},{"name":"424 Failed Dependency (RFC 4918)","path":"rfc4918#section-11.4","type":"Status","url":"/doc/html/rfc4918#section-11.4"},{"name":"425 Too Early","path":"status/425","type":"Status","url":"/en-US/docs/Web/HTTP/Status/425"},{"name":"426 Upgrade Required","path":"status/426","type":"Status","url":"/en-US/docs/Web/HTTP/Status/426"},{"name":"426 Upgrade Required (RFC 7231)","path":"rfc7231#section-6.5.15","type":"Status","url":"/doc/html/rfc7231#section-6.5.15"},{"name":"428 Precondition Required","path":"status/428","type":"Status","url":"/en-US/docs/Web/HTTP/Status/428"},{"name":"429 Too Many Requests","path":"status/429","type":"Status","url":"/en-US/docs/Web/HTTP/Status/429"},{"name":"431 Request Header Fields Too Large","path":"status/431","type":"Status","url":"/en-US/docs/Web/HTTP/Status/431"},{"name":"451 Unavailable For Legal Reasons","path":"status/451","type":"Status","url":"/en-US/docs/Web/HTTP/Status/451"},{"name":"500 Internal Server Error","path":"status/500","type":"Status","url":"/en-US/docs/Web/HTTP/Status/500"},{"name":"500 Internal Server Error (RFC 7231)","path":"rfc7231#section-6.6.1","type":"Status","url":"/doc/html/rfc7231#section-6.6.1"},{"name":"501 Not Implemented","path":"status/501","type":"Status","url":"/en-US/docs/Web/HTTP/Status/501"},{"name":"501 Not Implemented (RFC 7231)","path":"rfc7231#section-6.6.2","type":"Status","url":"/doc/html/rfc7231#section-6.6.2"},{"name":"502 Bad Gateway","path":"status/502","type":"Status","url":"/en-US/docs/Web/HTTP/Status/502"},{"name":"502 Bad Gateway (RFC 7231)","path":"rfc7231#section-6.6.3","type":"Status","url":"/doc/html/rfc7231#section-6.6.3"},{"name":"503 Service Unavailable","path":"status/503","type":"Status","url":"/en-US/docs/Web/HTTP/Status/503"},{"name":"503 Service Unavailable (RFC 7231)","path":"rfc7231#section-6.6.4","type":"Status","url":"/doc/html/rfc7231#section-6.6.4"},{"name":"504 Gateway Timeout","path":"status/504","type":"Status","url":"/en-US/docs/Web/HTTP/Status/504"},{"name":"504 Gateway Timeout (RFC 7231)","path":"rfc7231#section-6.6.5","type":"Status","url":"/doc/html/rfc7231#section-6.6.5"},{"name":"505 HTTP Version Not Supported","path":"status/505","type":"Status","url":"/en-US/docs/Web/HTTP/Status/505"},{"name":"505 HTTP Version Not Supported (RFC 7231)","path":"rfc7231#section-6.6.6","type":"Status","url":"/doc/html/rfc7231#section-6.6.6"},{"name":"506 Variant Also Negotiates","path":"status/506","type":"Status","url":"/en-US/docs/Web/HTTP/Status/506"},{"name":"507 Insufficient Storage","path":"status/507","type":"Status","url":"/en-US/docs/Web/HTTP/Status/507"},{"name":"507 Insufficient Storage (RFC 4918)","path":"rfc4918#section-11.5","type":"Status","url":"/doc/html/rfc4918#section-11.5"},{"name":"508 Loop Detected","path":"status/508","type":"Status","url":"/en-US/docs/Web/HTTP/Status/508"},{"name":"510 Not Extended","path":"status/510","type":"Status","url":"/en-US/docs/Web/HTTP/Status/510"},{"name":"511 Network Authentication Required","path":"status/511","type":"Status","url":"/en-US/docs/Web/HTTP/Status/511"},{"name":"ABNF List Extension: #rule (RFC 7230)","path":"rfc7230#section-7","type":"RFC 7230: Message Syntax and Routing","url":"/doc/html/rfc7230#section-7"},{"name":"Accept","path":"headers/accept","type":"Headers","url":"/en-US/docs/Web/HTTP/Headers/Accept"},{"name":"Accept (RFC 2616)","path":"rfc2616#section-14.1","type":"Headers","url":"/doc/html/rfc2616#section-14.1"},{"name":"Accept (RFC 7231)","path":"rfc7231#section-5.3.2","type":"Headers","url":"/doc/html/rfc7231#section-5.3.2"},{"name":"Accept-CH","path":"headers/accept-ch","type":"Headers","url":"/en-US/docs/Web/HTTP/Headers/Accept-CH"},{"name":"Accept-CH-Lifetime","path":"headers/accept-ch-lifetime","type":"Headers","url":"/en-US/docs/Web/HTTP/Headers/Accept-CH-Lifetime"},{"name":"Accept-Charset (RFC 2616)","path":"rfc2616#section-14.2","type":"Headers","url":"/doc/html/rfc2616#section-14.2"},{"name":"Accept-Charset (RFC 7231)","path":"rfc7231#section-5.3.3","type":"Headers","url":"/doc/html/rfc7231#section-5.3.3"},{"name":"Accept-Encoding","path":"headers/accept-encoding","type":"Headers","url":"/en-US/docs/Web/HTTP/Headers/Accept-Encoding"},{"name":"Accept-Encoding (RFC 2616)","path":"rfc2616#section-14.3","type":"Headers","url":"/doc/html/rfc2616#section-14.3"},{"name":"Accept-Encoding (RFC 7231)","path":"rfc7231#section-5.3.4","type":"Headers","url":"/doc/html/rfc7231#section-5.3.4"},{"name":"Accept-Language","path":"headers/accept-language","type":"Headers","url":"/en-US/docs/Web/HTTP/Headers/Accept-Language"},{"name":"Accept-Language (RFC 2616)","path":"rfc2616#section-14.4","type":"Headers","url":"/doc/html/rfc2616#section-14.4"},{"name":"Accept-Language (RFC 7231)","path":"rfc7231#section-5.3.5","type":"Headers","url":"/doc/html/rfc7231#section-5.3.5"},{"name":"Accept-Patch","path":"headers/accept-patch","type":"Headers","url":"/en-US/docs/Web/HTTP/Headers/Accept-Patch"},{"name":"Accept-Ranges","path":"headers/accept-ranges","type":"Headers","url":"/en-US/docs/Web/HTTP/Headers/Accept-Ranges"},{"name":"Accept-Ranges (RFC 2616)","path":"rfc2616#section-14.5","type":"Headers","url":"/doc/html/rfc2616#section-14.5"},{"name":"Access Authentication (RFC 2616)","path":"rfc2616#section-11","type":"RFC 2616: HTTP/1.1","url":"/doc/html/rfc2616#section-11"},{"name":"Access-Control-Allow-Credentials","path":"headers/access-control-allow-credentials","type":"Headers","url":"/en-US/docs/Web/HTTP/Headers/Access-Control-Allow-Credentials"},{"name":"Access-Control-Allow-Headers","path":"headers/access-control-allow-headers","type":"Headers","url":"/en-US/docs/Web/HTTP/Headers/Access-Control-Allow-Headers"},{"name":"Access-Control-Allow-Methods","path":"headers/access-control-allow-methods","type":"Headers","url":"/en-US/docs/Web/HTTP/Headers/Access-Control-Allow-Methods"},{"name":"Access-Control-Allow-Origin","path":"headers/access-control-allow-origin","type":"Headers","url":"/en-US/docs/Web/HTTP/Headers/Access-Control-Allow-Origin"},{"name":"Access-Control-Expose-Headers","path":"headers/access-control-expose-headers","type":"Headers","url":"/en-US/docs/Web/HTTP/Headers/Access-Control-Expose-Headers"},{"name":"Access-Control-Max-Age","path":"headers/access-control-max-age","type":"Headers","url":"/en-US/docs/Web/HTTP/Headers/Access-Control-Max-Age"},{"name":"Access-Control-Request-Headers","path":"headers/access-control-request-headers","type":"Headers","url":"/en-US/docs/Web/HTTP/Headers/Access-Control-Request-Headers"},{"name":"Access-Control-Request-Method","path":"headers/access-control-request-method","type":"Headers","url":"/en-US/docs/Web/HTTP/Headers/Access-Control-Request-Method"},{"name":"Age","path":"headers/age","type":"Headers","url":"/en-US/docs/Web/HTTP/Headers/Age"},{"name":"Age (RFC 2616)","path":"rfc2616#section-14.6","type":"Headers","url":"/doc/html/rfc2616#section-14.6"},{"name":"Allow","path":"headers/allow","type":"Headers","url":"/en-US/docs/Web/HTTP/Headers/Allow"},{"name":"Allow (RFC 2616)","path":"rfc2616#section-14.7","type":"Headers","url":"/doc/html/rfc2616#section-14.7"},{"name":"Allow (RFC 7231)","path":"rfc7231#section-7.4.1","type":"Headers","url":"/doc/html/rfc7231#section-7.4.1"},{"name":"Alt-Svc","path":"headers/alt-svc","type":"Headers","url":"/en-US/docs/Web/HTTP/Headers/Alt-Svc"},{"name":"Architecture (RFC 7230)","path":"rfc7230#section-2","type":"RFC 7230: Message Syntax and Routing","url":"/doc/html/rfc7230#section-2"},{"name":"Authentication","path":"authentication","type":"Guides","url":"/en-US/docs/Web/HTTP/Authentication"},{"name":"Authorization","path":"headers/authorization","type":"Headers","url":"/en-US/docs/Web/HTTP/Headers/Authorization"},{"name":"Authorization (RFC 2616)","path":"rfc2616#section-14.8","type":"Headers","url":"/doc/html/rfc2616#section-14.8"},{"name":"Browser detection using the user agent","path":"browser_detection_using_the_user_agent","type":"Guides","url":"/en-US/docs/Web/HTTP/Browser_detection_using_the_user_agent"},{"name":"Cache-Control","path":"headers/cache-control","type":"Headers","url":"/en-US/docs/Web/HTTP/Headers/Cache-Control"},{"name":"Cache-Control (RFC 2616)","path":"rfc2616#section-14.9","type":"Headers","url":"/doc/html/rfc2616#section-14.9"},{"name":"Cacheable Methods (RFC 7231)","path":"rfc7231#section-4.2.3","type":"Methods","url":"/doc/html/rfc7231#section-4.2.3"},{"name":"Caching","path":"caching","type":"Guides","url":"/en-US/docs/Web/HTTP/Caching"},{"name":"Caching in HTTP (RFC 2616)","path":"rfc2616#section-13","type":"RFC 2616: HTTP/1.1","url":"/doc/html/rfc2616#section-13"},{"name":"Client hints","path":"client_hints","type":"Guides","url":"/en-US/docs/Web/HTTP/Client_hints"},{"name":"Conditional requests","path":"conditional_requests","type":"Guides","url":"/en-US/docs/Web/HTTP/Conditional_requests"},{"name":"CONNECT","path":"methods/connect","type":"Methods","url":"/en-US/docs/Web/HTTP/Methods/CONNECT"},{"name":"CONNECT (RFC 7231)","path":"rfc7231#section-4.3.6","type":"Methods","url":"/doc/html/rfc7231#section-4.3.6"},{"name":"Connection","path":"headers/connection","type":"Headers","url":"/en-US/docs/Web/HTTP/Headers/Connection"},{"name":"Connection (RFC 2616)","path":"rfc2616#section-14.10","type":"Headers","url":"/doc/html/rfc2616#section-14.10"},{"name":"Connection Management (RFC 7230)","path":"rfc7230#section-6","type":"RFC 7230: Message Syntax and Routing","url":"/doc/html/rfc7230#section-6"},{"name":"Connection management in HTTP 1.x","path":"connection_management_in_http_1.x","type":"Guides","url":"/en-US/docs/Web/HTTP/Connection_management_in_HTTP_1.x"},{"name":"Connections (RFC 2616)","path":"rfc2616#section-8","type":"RFC 2616: HTTP/1.1","url":"/doc/html/rfc2616#section-8"},{"name":"Content negotiation","path":"content_negotiation","type":"Guides","url":"/en-US/docs/Web/HTTP/Content_negotiation"},{"name":"Content Negotiation (RFC 2616)","path":"rfc2616#section-12","type":"RFC 2616: HTTP/1.1","url":"/doc/html/rfc2616#section-12"},{"name":"Content negotiation: List of default Accept values","path":"content_negotiation/list_of_default_accept_values","type":"Guides","url":"/en-US/docs/Web/HTTP/Content_negotiation/List_of_default_Accept_values"},{"name":"Content-Disposition","path":"headers/content-disposition","type":"Headers","url":"/en-US/docs/Web/HTTP/Headers/Content-Disposition"},{"name":"Content-DPR","path":"headers/content-dpr","type":"Headers","url":"/en-US/docs/Web/HTTP/Headers/Content-DPR"},{"name":"Content-Encoding","path":"headers/content-encoding","type":"Headers","url":"/en-US/docs/Web/HTTP/Headers/Content-Encoding"},{"name":"Content-Encoding (RFC 2616)","path":"rfc2616#section-14.11","type":"Headers","url":"/doc/html/rfc2616#section-14.11"},{"name":"Content-Language","path":"headers/content-language","type":"Headers","url":"/en-US/docs/Web/HTTP/Headers/Content-Language"},{"name":"Content-Language (RFC 2616)","path":"rfc2616#section-14.12","type":"Headers","url":"/doc/html/rfc2616#section-14.12"},{"name":"Content-Length","path":"headers/content-length","type":"Headers","url":"/en-US/docs/Web/HTTP/Headers/Content-Length"},{"name":"Content-Length (RFC 2616)","path":"rfc2616#section-14.13","type":"Headers","url":"/doc/html/rfc2616#section-14.13"},{"name":"Content-Location","path":"headers/content-location","type":"Headers","url":"/en-US/docs/Web/HTTP/Headers/Content-Location"},{"name":"Content-Location (RFC 2616)","path":"rfc2616#section-14.14","type":"Headers","url":"/doc/html/rfc2616#section-14.14"},{"name":"Content-MD5 (RFC 2616)","path":"rfc2616#section-14.15","type":"Headers","url":"/doc/html/rfc2616#section-14.15"},{"name":"Content-Range","path":"headers/content-range","type":"Headers","url":"/en-US/docs/Web/HTTP/Headers/Content-Range"},{"name":"Content-Range (RFC 2616)","path":"rfc2616#section-14.16","type":"Headers","url":"/doc/html/rfc2616#section-14.16"},{"name":"Content-Security-Policy","path":"headers/content-security-policy","type":"CSP","url":"/en-US/docs/Web/HTTP/Headers/Content-Security-Policy"},{"name":"Content-Security-Policy-Report-Only","path":"headers/content-security-policy-report-only","type":"CSP","url":"/en-US/docs/Web/HTTP/Headers/Content-Security-Policy-Report-Only"},{"name":"Content-Type","path":"headers/content-type","type":"Headers","url":"/en-US/docs/Web/HTTP/Headers/Content-Type"},{"name":"Content-Type (RFC 2616)","path":"rfc2616#section-14.17","type":"Headers","url":"/doc/html/rfc2616#section-14.17"},{"name":"Cookie","path":"headers/cookie","type":"Headers","url":"/en-US/docs/Web/HTTP/Headers/Cookie"},{"name":"Cookies","path":"cookies","type":"Guides","url":"/en-US/docs/Web/HTTP/Cookies"},{"name":"CORS","path":"cors","type":"Guides","url":"/en-US/docs/Web/HTTP/CORS"},{"name":"Cross-Origin Resource Policy (CORP)","path":"cross-origin_resource_policy_(corp)","type":"Guides","url":"/en-US/docs/Web/HTTP/Cross-Origin_Resource_Policy_(CORP)"},{"name":"Cross-Origin-Embedder-Policy","path":"headers/cross-origin-embedder-policy","type":"Headers","url":"/en-US/docs/Web/HTTP/Headers/Cross-Origin-Embedder-Policy"},{"name":"Cross-Origin-Opener-Policy","path":"headers/cross-origin-opener-policy","type":"Headers","url":"/en-US/docs/Web/HTTP/Headers/Cross-Origin-Opener-Policy"},{"name":"Cross-Origin-Resource-Policy","path":"headers/cross-origin-resource-policy","type":"Headers","url":"/en-US/docs/Web/HTTP/Headers/Cross-Origin-Resource-Policy"},{"name":"CSP","path":"csp","type":"Guides","url":"/en-US/docs/Web/HTTP/CSP"},{"name":"CSP: base-uri","path":"headers/content-security-policy/base-uri","type":"CSP","url":"/en-US/docs/Web/HTTP/Headers/Content-Security-Policy/base-uri"},{"name":"CSP: block-all-mixed-content","path":"headers/content-security-policy/block-all-mixed-content","type":"CSP","url":"/en-US/docs/Web/HTTP/Headers/Content-Security-Policy/block-all-mixed-content"},{"name":"CSP: child-src","path":"headers/content-security-policy/child-src","type":"CSP","url":"/en-US/docs/Web/HTTP/Headers/Content-Security-Policy/child-src"},{"name":"CSP: connect-src","path":"headers/content-security-policy/connect-src","type":"CSP","url":"/en-US/docs/Web/HTTP/Headers/Content-Security-Policy/connect-src"},{"name":"CSP: default-src","path":"headers/content-security-policy/default-src","type":"CSP","url":"/en-US/docs/Web/HTTP/Headers/Content-Security-Policy/default-src"},{"name":"CSP: font-src","path":"headers/content-security-policy/font-src","type":"CSP","url":"/en-US/docs/Web/HTTP/Headers/Content-Security-Policy/font-src"},{"name":"CSP: form-action","path":"headers/content-security-policy/form-action","type":"CSP","url":"/en-US/docs/Web/HTTP/Headers/Content-Security-Policy/form-action"},{"name":"CSP: frame-ancestors","path":"headers/content-security-policy/frame-ancestors","type":"CSP","url":"/en-US/docs/Web/HTTP/Headers/Content-Security-Policy/frame-ancestors"},{"name":"CSP: frame-src","path":"headers/content-security-policy/frame-src","type":"CSP","url":"/en-US/docs/Web/HTTP/Headers/Content-Security-Policy/frame-src"},{"name":"CSP: img-src","path":"headers/content-security-policy/img-src","type":"CSP","url":"/en-US/docs/Web/HTTP/Headers/Content-Security-Policy/img-src"},{"name":"CSP: manifest-src","path":"headers/content-security-policy/manifest-src","type":"CSP","url":"/en-US/docs/Web/HTTP/Headers/Content-Security-Policy/manifest-src"},{"name":"CSP: media-src","path":"headers/content-security-policy/media-src","type":"CSP","url":"/en-US/docs/Web/HTTP/Headers/Content-Security-Policy/media-src"},{"name":"CSP: navigate-to","path":"headers/content-security-policy/navigate-to","type":"CSP","url":"/en-US/docs/Web/HTTP/Headers/Content-Security-Policy/navigate-to"},{"name":"CSP: object-src","path":"headers/content-security-policy/object-src","type":"CSP","url":"/en-US/docs/Web/HTTP/Headers/Content-Security-Policy/object-src"},{"name":"CSP: plugin-types","path":"headers/content-security-policy/plugin-types","type":"CSP","url":"/en-US/docs/Web/HTTP/Headers/Content-Security-Policy/plugin-types"},{"name":"CSP: prefetch-src","path":"headers/content-security-policy/prefetch-src","type":"CSP","url":"/en-US/docs/Web/HTTP/Headers/Content-Security-Policy/prefetch-src"},{"name":"CSP: referrer","path":"headers/content-security-policy/referrer","type":"CSP","url":"/en-US/docs/Web/HTTP/Headers/Content-Security-Policy/referrer"},{"name":"CSP: report-to","path":"headers/content-security-policy/report-to","type":"CSP","url":"/en-US/docs/Web/HTTP/Headers/Content-Security-Policy/report-to"},{"name":"CSP: report-uri","path":"headers/content-security-policy/report-uri","type":"CSP","url":"/en-US/docs/Web/HTTP/Headers/Content-Security-Policy/report-uri"},{"name":"CSP: require-sri-for","path":"headers/content-security-policy/require-sri-for","type":"CSP","url":"/en-US/docs/Web/HTTP/Headers/Content-Security-Policy/require-sri-for"},{"name":"CSP: require-trusted-types-for","path":"headers/content-security-policy/require-trusted-types-for","type":"CSP","url":"/en-US/docs/Web/HTTP/Headers/Content-Security-Policy/require-trusted-types-for"},{"name":"CSP: sandbox","path":"headers/content-security-policy/sandbox","type":"CSP","url":"/en-US/docs/Web/HTTP/Headers/Content-Security-Policy/sandbox"},{"name":"CSP: script-src","path":"headers/content-security-policy/script-src","type":"CSP","url":"/en-US/docs/Web/HTTP/Headers/Content-Security-Policy/script-src"},{"name":"CSP: script-src-attr","path":"headers/content-security-policy/script-src-attr","type":"CSP","url":"/en-US/docs/Web/HTTP/Headers/Content-Security-Policy/script-src-attr"},{"name":"CSP: script-src-elem","path":"headers/content-security-policy/script-src-elem","type":"CSP","url":"/en-US/docs/Web/HTTP/Headers/Content-Security-Policy/script-src-elem"},{"name":"CSP: style-src","path":"headers/content-security-policy/style-src","type":"CSP","url":"/en-US/docs/Web/HTTP/Headers/Content-Security-Policy/style-src"},{"name":"CSP: style-src-attr","path":"headers/content-security-policy/style-src-attr","type":"CSP","url":"/en-US/docs/Web/HTTP/Headers/Content-Security-Policy/style-src-attr"},{"name":"CSP: style-src-elem","path":"headers/content-security-policy/style-src-elem","type":"CSP","url":"/en-US/docs/Web/HTTP/Headers/Content-Security-Policy/style-src-elem"},{"name":"CSP: trusted-types","path":"headers/content-security-policy/trusted-types","type":"CSP","url":"/en-US/docs/Web/HTTP/Headers/Content-Security-Policy/trusted-types"},{"name":"CSP: upgrade-insecure-requests","path":"headers/content-security-policy/upgrade-insecure-requests","type":"CSP","url":"/en-US/docs/Web/HTTP/Headers/Content-Security-Policy/upgrade-insecure-requests"},{"name":"CSP: worker-src","path":"headers/content-security-policy/worker-src","type":"CSP","url":"/en-US/docs/Web/HTTP/Headers/Content-Security-Policy/worker-src"},{"name":"Data URIs","path":"basics_of_http/data_uris","type":"Guides: Basics","url":"/en-US/docs/Web/HTTP/Basics_of_HTTP/Data_URIs"},{"name":"Date","path":"headers/date","type":"Headers","url":"/en-US/docs/Web/HTTP/Headers/Date"},{"name":"Date (RFC 2616)","path":"rfc2616#section-14.18","type":"Headers","url":"/doc/html/rfc2616#section-14.18"},{"name":"DELETE","path":"methods/delete","type":"Methods","url":"/en-US/docs/Web/HTTP/Methods/DELETE"},{"name":"DELETE (RFC 7231)","path":"rfc7231#section-4.3.5","type":"Methods","url":"/doc/html/rfc7231#section-4.3.5"},{"name":"Device-Memory","path":"headers/device-memory","type":"Headers","url":"/en-US/docs/Web/HTTP/Headers/Device-Memory"},{"name":"DNT","path":"headers/dnt","type":"Headers","url":"/en-US/docs/Web/HTTP/Headers/DNT"},{"name":"Downlink","path":"headers/downlink","type":"Headers","url":"/en-US/docs/Web/HTTP/Headers/Downlink"},{"name":"DPR","path":"headers/dpr","type":"Headers","url":"/en-US/docs/Web/HTTP/Headers/DPR"},{"name":"ECT","path":"headers/ect","type":"Headers","url":"/en-US/docs/Web/HTTP/Headers/ECT"},{"name":"Entity (RFC 2616)","path":"rfc2616#section-7","type":"RFC 2616: HTTP/1.1","url":"/doc/html/rfc2616#section-7"},{"name":"Errors","path":"cors/errors","type":"Guides","url":"/en-US/docs/Web/HTTP/CORS/Errors"},{"name":"Errors: CORSAllowOriginNotMatchingOrigin","path":"cors/errors/corsalloworiginnotmatchingorigin","type":"Guides","url":"/en-US/docs/Web/HTTP/CORS/Errors/CORSAllowOriginNotMatchingOrigin"},{"name":"Errors: CORSDidNotSucceed","path":"cors/errors/corsdidnotsucceed","type":"Guides","url":"/en-US/docs/Web/HTTP/CORS/Errors/CORSDidNotSucceed"},{"name":"Errors: CORSDisabled","path":"cors/errors/corsdisabled","type":"Guides","url":"/en-US/docs/Web/HTTP/CORS/Errors/CORSDisabled"},{"name":"Errors: CORSExternalRedirectNotAllowed","path":"cors/errors/corsexternalredirectnotallowed","type":"Guides","url":"/en-US/docs/Web/HTTP/CORS/Errors/CORSExternalRedirectNotAllowed"},{"name":"Errors: CORSInvalidAllowHeader","path":"cors/errors/corsinvalidallowheader","type":"Guides","url":"/en-US/docs/Web/HTTP/CORS/Errors/CORSInvalidAllowHeader"},{"name":"Errors: CORSInvalidAllowMethod","path":"cors/errors/corsinvalidallowmethod","type":"Guides","url":"/en-US/docs/Web/HTTP/CORS/Errors/CORSInvalidAllowMethod"},{"name":"Errors: CORSMethodNotFound","path":"cors/errors/corsmethodnotfound","type":"Guides","url":"/en-US/docs/Web/HTTP/CORS/Errors/CORSMethodNotFound"},{"name":"Errors: CORSMIssingAllowCredentials","path":"cors/errors/corsmissingallowcredentials","type":"Guides","url":"/en-US/docs/Web/HTTP/CORS/Errors/CORSMIssingAllowCredentials"},{"name":"Errors: CORSMissingAllowHeaderFromPreflight","path":"cors/errors/corsmissingallowheaderfrompreflight","type":"Guides","url":"/en-US/docs/Web/HTTP/CORS/Errors/CORSMissingAllowHeaderFromPreflight"},{"name":"Errors: CORSMissingAllowOrigin","path":"cors/errors/corsmissingalloworigin","type":"Guides","url":"/en-US/docs/Web/HTTP/CORS/Errors/CORSMissingAllowOrigin"},{"name":"Errors: CORSMultipleAllowOriginNotAllowed","path":"cors/errors/corsmultiplealloworiginnotallowed","type":"Guides","url":"/en-US/docs/Web/HTTP/CORS/Errors/CORSMultipleAllowOriginNotAllowed"},{"name":"Errors: CORSNotSupportingCredentials","path":"cors/errors/corsnotsupportingcredentials","type":"Guides","url":"/en-US/docs/Web/HTTP/CORS/Errors/CORSNotSupportingCredentials"},{"name":"Errors: CORSOriginHeaderNotAdded","path":"cors/errors/corsoriginheadernotadded","type":"Guides","url":"/en-US/docs/Web/HTTP/CORS/Errors/CORSOriginHeaderNotAdded"},{"name":"Errors: CORSPreflightDidNotSucceed","path":"cors/errors/corspreflightdidnotsucceed","type":"Guides","url":"/en-US/docs/Web/HTTP/CORS/Errors/CORSPreflightDidNotSucceed"},{"name":"Errors: CORSRequestNotHttp","path":"cors/errors/corsrequestnothttp","type":"Guides","url":"/en-US/docs/Web/HTTP/CORS/Errors/CORSRequestNotHttp"},{"name":"ETag","path":"headers/etag","type":"Headers","url":"/en-US/docs/Web/HTTP/Headers/ETag"},{"name":"ETag (RFC 2616)","path":"rfc2616#section-14.19","type":"Headers","url":"/doc/html/rfc2616#section-14.19"},{"name":"Evolution of HTTP","path":"basics_of_http/evolution_of_http","type":"Guides: Basics","url":"/en-US/docs/Web/HTTP/Basics_of_HTTP/Evolution_of_HTTP"},{"name":"Expect","path":"headers/expect","type":"Headers","url":"/en-US/docs/Web/HTTP/Headers/Expect"},{"name":"Expect (RFC 2616)","path":"rfc2616#section-14.20","type":"Headers","url":"/doc/html/rfc2616#section-14.20"},{"name":"Expect (RFC 7231)","path":"rfc7231#section-5.1.1","type":"Headers","url":"/doc/html/rfc7231#section-5.1.1"},{"name":"Expires","path":"headers/expires","type":"Headers","url":"/en-US/docs/Web/HTTP/Headers/Expires"},{"name":"Expires (RFC 2616)","path":"rfc2616#section-14.21","type":"Headers","url":"/doc/html/rfc2616#section-14.21"},{"name":"Forwarded","path":"headers/forwarded","type":"Headers","url":"/en-US/docs/Web/HTTP/Headers/Forwarded"},{"name":"From (RFC 2616)","path":"rfc2616#section-14.22","type":"Headers","url":"/doc/html/rfc2616#section-14.22"},{"name":"From (RFC 7231)","path":"rfc7231#section-5.5.1","type":"Headers","url":"/doc/html/rfc7231#section-5.5.1"},{"name":"GET","path":"methods/get","type":"Methods","url":"/en-US/docs/Web/HTTP/Methods/GET"},{"name":"GET (RFC 7231)","path":"rfc7231#section-4.3.1","type":"Methods","url":"/doc/html/rfc7231#section-4.3.1"},{"name":"HEAD","path":"methods/head","type":"Methods","url":"/en-US/docs/Web/HTTP/Methods/HEAD"},{"name":"HEAD (RFC 7231)","path":"rfc7231#section-4.3.2","type":"Methods","url":"/doc/html/rfc7231#section-4.3.2"},{"name":"Host","path":"headers/host","type":"Headers","url":"/en-US/docs/Web/HTTP/Headers/Host"},{"name":"Host (RFC 2616)","path":"rfc2616#section-14.23","type":"Headers","url":"/doc/html/rfc2616#section-14.23"},{"name":"HTTP Message (RFC 2616)","path":"rfc2616#section-4","type":"RFC 2616: HTTP/1.1","url":"/doc/html/rfc2616#section-4"},{"name":"IANA Considerations (RFC 7230)","path":"rfc7230#section-8","type":"RFC 7230: Message Syntax and Routing","url":"/doc/html/rfc7230#section-8"},{"name":"IANA Considerations (RFC 7231)","path":"rfc7231#section-8","type":"RFC 7231: Semantics and Content","url":"/doc/html/rfc7231#section-8"},{"name":"Idempotent Methods (RFC 7231)","path":"rfc7231#section-4.2.2","type":"Methods","url":"/doc/html/rfc7231#section-4.2.2"},{"name":"Identifying resources on the Web","path":"basics_of_http/identifying_resources_on_the_web","type":"Guides: Basics","url":"/en-US/docs/Web/HTTP/Basics_of_HTTP/Identifying_resources_on_the_Web"},{"name":"If-Match","path":"headers/if-match","type":"Headers","url":"/en-US/docs/Web/HTTP/Headers/If-Match"},{"name":"If-Match (RFC 2616)","path":"rfc2616#section-14.24","type":"Headers","url":"/doc/html/rfc2616#section-14.24"},{"name":"If-Modified-Since","path":"headers/if-modified-since","type":"Headers","url":"/en-US/docs/Web/HTTP/Headers/If-Modified-Since"},{"name":"If-Modified-Since (RFC 2616)","path":"rfc2616#section-14.25","type":"Headers","url":"/doc/html/rfc2616#section-14.25"},{"name":"If-None-Match","path":"headers/if-none-match","type":"Headers","url":"/en-US/docs/Web/HTTP/Headers/If-None-Match"},{"name":"If-None-Match (RFC 2616)","path":"rfc2616#section-14.26","type":"Headers","url":"/doc/html/rfc2616#section-14.26"},{"name":"If-Range","path":"headers/if-range","type":"Headers","url":"/en-US/docs/Web/HTTP/Headers/If-Range"},{"name":"If-Range (RFC 2616)","path":"rfc2616#section-14.27","type":"Headers","url":"/doc/html/rfc2616#section-14.27"},{"name":"If-Unmodified-Since","path":"headers/if-unmodified-since","type":"Headers","url":"/en-US/docs/Web/HTTP/Headers/If-Unmodified-Since"},{"name":"If-Unmodified-Since (RFC 2616)","path":"rfc2616#section-14.28","type":"Headers","url":"/doc/html/rfc2616#section-14.28"},{"name":"Keep-Alive","path":"headers/keep-alive","type":"Headers","url":"/en-US/docs/Web/HTTP/Headers/Keep-Alive"},{"name":"Last-Modified","path":"headers/last-modified","type":"Headers","url":"/en-US/docs/Web/HTTP/Headers/Last-Modified"},{"name":"Last-Modified (RFC 2616)","path":"rfc2616#section-14.29","type":"Headers","url":"/doc/html/rfc2616#section-14.29"},{"name":"Link","path":"headers/link","type":"Headers","url":"/en-US/docs/Web/HTTP/Headers/Link"},{"name":"Location","path":"headers/location","type":"Headers","url":"/en-US/docs/Web/HTTP/Headers/Location"},{"name":"Location (RFC 2616)","path":"rfc2616#section-14.30","type":"Headers","url":"/doc/html/rfc2616#section-14.30"},{"name":"Location (RFC 7231)","path":"rfc7231#section-7.1.2","type":"Headers","url":"/doc/html/rfc7231#section-7.1.2"},{"name":"Max-Forwards (RFC 2616)","path":"rfc2616#section-14.31","type":"Headers","url":"/doc/html/rfc2616#section-14.31"},{"name":"Max-Forwards (RFC 7231)","path":"rfc7231#section-5.1.2","type":"Headers","url":"/doc/html/rfc7231#section-5.1.2"},{"name":"Message Format (RFC 7230)","path":"rfc7230#section-3","type":"RFC 7230: Message Syntax and Routing","url":"/doc/html/rfc7230#section-3"},{"name":"Message Routing (RFC 7230)","path":"rfc7230#section-5","type":"RFC 7230: Message Syntax and Routing","url":"/doc/html/rfc7230#section-5"},{"name":"Messages","path":"messages","type":"Guides","url":"/en-US/docs/Web/HTTP/Messages"},{"name":"Method Definitions (RFC 2616)","path":"rfc2616#section-9","type":"RFC 2616: HTTP/1.1","url":"/doc/html/rfc2616#section-9"},{"name":"Methods","path":"methods","type":"Methods","url":"/en-US/docs/Web/HTTP/Methods"},{"name":"MIME types","path":"basics_of_http/mime_types","type":"Guides: Basics","url":"/en-US/docs/Web/HTTP/Basics_of_HTTP/MIME_types"},{"name":"MIME types: Common types","path":"basics_of_http/mime_types/common_types","type":"Guides: Basics","url":"/en-US/docs/Web/HTTP/Basics_of_HTTP/MIME_types/Common_types"},{"name":"OPTIONS","path":"methods/options","type":"Methods","url":"/en-US/docs/Web/HTTP/Methods/OPTIONS"},{"name":"OPTIONS (RFC 7231)","path":"rfc7231#section-4.3.7","type":"Methods","url":"/doc/html/rfc7231#section-4.3.7"},{"name":"Origin","path":"headers/origin","type":"Headers","url":"/en-US/docs/Web/HTTP/Headers/Origin"},{"name":"Overview","path":"overview","type":"Guides","url":"/en-US/docs/Web/HTTP/Overview"},{"name":"PATCH","path":"methods/patch","type":"Methods","url":"/en-US/docs/Web/HTTP/Methods/PATCH"},{"name":"POST","path":"methods/post","type":"Methods","url":"/en-US/docs/Web/HTTP/Methods/POST"},{"name":"POST (RFC 7231)","path":"rfc7231#section-4.3.3","type":"Methods","url":"/doc/html/rfc7231#section-4.3.3"},{"name":"Pragma","path":"headers/pragma","type":"Headers","url":"/en-US/docs/Web/HTTP/Headers/Pragma"},{"name":"Pragma (RFC 2616)","path":"rfc2616#section-14.32","type":"Headers","url":"/doc/html/rfc2616#section-14.32"},{"name":"Protocol Parameters (RFC 2616)","path":"rfc2616#section-3","type":"RFC 2616: HTTP/1.1","url":"/doc/html/rfc2616#section-3"},{"name":"Protocol upgrade mechanism","path":"protocol_upgrade_mechanism","type":"Guides","url":"/en-US/docs/Web/HTTP/Protocol_upgrade_mechanism"},{"name":"Proxy servers and tunneling","path":"proxy_servers_and_tunneling","type":"Guides","url":"/en-US/docs/Web/HTTP/Proxy_servers_and_tunneling"},{"name":"Proxy servers and tunneling: Proxy Auto-Configuration PAC file","path":"proxy_servers_and_tunneling/proxy_auto-configuration_pac_file","type":"Guides","url":"/en-US/docs/Web/HTTP/Proxy_servers_and_tunneling/Proxy_Auto-Configuration_PAC_file"},{"name":"Proxy-Authenticate","path":"headers/proxy-authenticate","type":"Headers","url":"/en-US/docs/Web/HTTP/Headers/Proxy-Authenticate"},{"name":"Proxy-Authenticate (RFC 2616)","path":"rfc2616#section-14.33","type":"Headers","url":"/doc/html/rfc2616#section-14.33"},{"name":"Proxy-Authorization","path":"headers/proxy-authorization","type":"Headers","url":"/en-US/docs/Web/HTTP/Headers/Proxy-Authorization"},{"name":"Proxy-Authorization (RFC 2616)","path":"rfc2616#section-14.34","type":"Headers","url":"/doc/html/rfc2616#section-14.34"},{"name":"PUT","path":"methods/put","type":"Methods","url":"/en-US/docs/Web/HTTP/Methods/PUT"},{"name":"PUT (RFC 7231)","path":"rfc7231#section-4.3.4","type":"Methods","url":"/doc/html/rfc7231#section-4.3.4"},{"name":"Quality Values (RFC 7231)","path":"rfc7231#section-5.3.1","type":"Headers","url":"/doc/html/rfc7231#section-5.3.1"},{"name":"Range","path":"headers/range","type":"Headers","url":"/en-US/docs/Web/HTTP/Headers/Range"},{"name":"Range (RFC 2616)","path":"rfc2616#section-14.35","type":"Headers","url":"/doc/html/rfc2616#section-14.35"},{"name":"Referer","path":"headers/referer","type":"Headers","url":"/en-US/docs/Web/HTTP/Headers/Referer"},{"name":"Referer (RFC 2616)","path":"rfc2616#section-14.36","type":"Headers","url":"/doc/html/rfc2616#section-14.36"},{"name":"Referer (RFC 7231)","path":"rfc7231#section-5.5.2","type":"Headers","url":"/doc/html/rfc7231#section-5.5.2"},{"name":"Referrer-Policy","path":"headers/referrer-policy","type":"Headers","url":"/en-US/docs/Web/HTTP/Headers/Referrer-Policy"},{"name":"Representations (RFC 7231)","path":"rfc7231#section-3","type":"RFC 7231: Semantics and Content","url":"/doc/html/rfc7231#section-3"},{"name":"Request (RFC 2616)","path":"rfc2616#section-5","type":"RFC 2616: HTTP/1.1","url":"/doc/html/rfc2616#section-5"},{"name":"Response (RFC 2616)","path":"rfc2616#section-6","type":"RFC 2616: HTTP/1.1","url":"/doc/html/rfc2616#section-6"},{"name":"Retry-After","path":"headers/retry-after","type":"Headers","url":"/en-US/docs/Web/HTTP/Headers/Retry-After"},{"name":"Retry-After (RFC 2616)","path":"rfc2616#section-14.37","type":"Headers","url":"/doc/html/rfc2616#section-14.37"},{"name":"Retry-After (RFC 7231)","path":"rfc7231#section-7.1.3","type":"Headers","url":"/doc/html/rfc7231#section-7.1.3"},{"name":"RFC 2616: HTTP/1.1","path":"rfc2616","type":"RFC 2616: HTTP/1.1","url":"/doc/html/rfc2616"},{"name":"RFC 4918: WebDAV","path":"rfc4918","type":"RFC 4918: WebDAV","url":"/doc/html/rfc4918"},{"name":"RFC 7230: Message Syntax and Routing","path":"rfc7230","type":"RFC 7230: Message Syntax and Routing","url":"/doc/html/rfc7230"},{"name":"RFC 7231: Semantics and Content","path":"rfc7231","type":"RFC 7231: Semantics and Content","url":"/doc/html/rfc7231"},{"name":"RTT","path":"headers/rtt","type":"Headers","url":"/en-US/docs/Web/HTTP/Headers/RTT"},{"name":"Safe Methods (RFC 7231)","path":"rfc7231#section-4.2.1","type":"Methods","url":"/doc/html/rfc7231#section-4.2.1"},{"name":"Save-Data","path":"headers/save-data","type":"Headers","url":"/en-US/docs/Web/HTTP/Headers/Save-Data"},{"name":"Sec-CH-UA","path":"headers/sec-ch-ua","type":"Headers","url":"/en-US/docs/Web/HTTP/Headers/Sec-CH-UA"},{"name":"Sec-CH-UA-Arch","path":"headers/sec-ch-ua-arch","type":"Headers","url":"/en-US/docs/Web/HTTP/Headers/Sec-CH-UA-Arch"},{"name":"Sec-CH-UA-Bitness","path":"headers/sec-ch-ua-bitness","type":"Headers","url":"/en-US/docs/Web/HTTP/Headers/Sec-CH-UA-Bitness"},{"name":"Sec-CH-UA-Full-Version","path":"headers/sec-ch-ua-full-version","type":"Headers","url":"/en-US/docs/Web/HTTP/Headers/Sec-CH-UA-Full-Version"},{"name":"Sec-CH-UA-Full-Version-List","path":"headers/sec-ch-ua-full-version-list","type":"Headers","url":"/en-US/docs/Web/HTTP/Headers/Sec-CH-UA-Full-Version-List"},{"name":"Sec-CH-UA-Mobile","path":"headers/sec-ch-ua-mobile","type":"Headers","url":"/en-US/docs/Web/HTTP/Headers/Sec-CH-UA-Mobile"},{"name":"Sec-CH-UA-Model","path":"headers/sec-ch-ua-model","type":"Headers","url":"/en-US/docs/Web/HTTP/Headers/Sec-CH-UA-Model"},{"name":"Sec-CH-UA-Platform","path":"headers/sec-ch-ua-platform","type":"Headers","url":"/en-US/docs/Web/HTTP/Headers/Sec-CH-UA-Platform"},{"name":"Sec-CH-UA-Platform-Version","path":"headers/sec-ch-ua-platform-version","type":"Headers","url":"/en-US/docs/Web/HTTP/Headers/Sec-CH-UA-Platform-Version"},{"name":"Sec-WebSocket-Accept","path":"headers/sec-websocket-accept","type":"Headers","url":"/en-US/docs/Web/HTTP/Headers/Sec-WebSocket-Accept"},{"name":"Security Considerations (RFC 2616)","path":"rfc2616#section-15","type":"RFC 2616: HTTP/1.1","url":"/doc/html/rfc2616#section-15"},{"name":"Security Considerations (RFC 7230)","path":"rfc7230#section-9","type":"RFC 7230: Message Syntax and Routing","url":"/doc/html/rfc7230#section-9"},{"name":"Security Considerations (RFC 7231)","path":"rfc7231#section-9","type":"RFC 7231: Semantics and Content","url":"/doc/html/rfc7231#section-9"},{"name":"Server","path":"headers/server","type":"Headers","url":"/en-US/docs/Web/HTTP/Headers/Server"},{"name":"Server (RFC 2616)","path":"rfc2616#section-14.38","type":"Headers","url":"/doc/html/rfc2616#section-14.38"},{"name":"Server (RFC 7231)","path":"rfc7231#section-7.4.2","type":"Headers","url":"/doc/html/rfc7231#section-7.4.2"},{"name":"Session","path":"session","type":"Guides","url":"/en-US/docs/Web/HTTP/Session"},{"name":"Set-Cookie","path":"headers/set-cookie","type":"Headers","url":"/en-US/docs/Web/HTTP/Headers/Set-Cookie"},{"name":"Set-Cookie: SameSite","path":"headers/set-cookie/samesite","type":"Headers","url":"/en-US/docs/Web/HTTP/Headers/Set-Cookie/SameSite"},{"name":"Status","path":"status","type":"Status","url":"/en-US/docs/Web/HTTP/Status"},{"name":"Status Code Definitions (RFC 2616)","path":"rfc2616#section-10","type":"RFC 2616: HTTP/1.1","url":"/doc/html/rfc2616#section-10"},{"name":"Strict-Transport-Security","path":"headers/strict-transport-security","type":"Headers","url":"/en-US/docs/Web/HTTP/Headers/Strict-Transport-Security"},{"name":"TE","path":"headers/te","type":"Headers","url":"/en-US/docs/Web/HTTP/Headers/TE"},{"name":"TE (RFC 2616)","path":"rfc2616#section-14.39","type":"Headers","url":"/doc/html/rfc2616#section-14.39"},{"name":"Tk","path":"headers/tk","type":"Headers","url":"/en-US/docs/Web/HTTP/Headers/Tk"},{"name":"TRACE","path":"methods/trace","type":"Methods","url":"/en-US/docs/Web/HTTP/Methods/TRACE"},{"name":"TRACE (RFC 7231)","path":"rfc7231#section-4.3.8","type":"Methods","url":"/doc/html/rfc7231#section-4.3.8"},{"name":"Trailer","path":"headers/trailer","type":"Headers","url":"/en-US/docs/Web/HTTP/Headers/Trailer"},{"name":"Trailer (RFC 2616)","path":"rfc2616#section-14.40","type":"Headers","url":"/doc/html/rfc2616#section-14.40"},{"name":"Transfer Codings (RFC 7230)","path":"rfc7230#section-4","type":"RFC 7230: Message Syntax and Routing","url":"/doc/html/rfc7230#section-4"},{"name":"Transfer-Encoding","path":"headers/transfer-encoding","type":"Headers","url":"/en-US/docs/Web/HTTP/Headers/Transfer-Encoding"},{"name":"Transfer-Encoding (RFC 2616)","path":"rfc2616#section-14.41","type":"Headers","url":"/doc/html/rfc2616#section-14.41"},{"name":"Upgrade","path":"headers/upgrade","type":"Headers","url":"/en-US/docs/Web/HTTP/Headers/Upgrade"},{"name":"Upgrade (RFC 2616)","path":"rfc2616#section-14.42","type":"Headers","url":"/doc/html/rfc2616#section-14.42"},{"name":"Upgrade-Insecure-Requests","path":"headers/upgrade-insecure-requests","type":"Headers","url":"/en-US/docs/Web/HTTP/Headers/Upgrade-Insecure-Requests"},{"name":"User-Agent","path":"headers/user-agent","type":"Headers","url":"/en-US/docs/Web/HTTP/Headers/User-Agent"},{"name":"User-Agent (RFC 2616)","path":"rfc2616#section-14.43","type":"Headers","url":"/doc/html/rfc2616#section-14.43"},{"name":"User-Agent (RFC 7231)","path":"rfc7231#section-5.5.3","type":"Headers","url":"/doc/html/rfc7231#section-5.5.3"},{"name":"User-Agent: Firefox","path":"headers/user-agent/firefox","type":"Headers","url":"/en-US/docs/Web/HTTP/Headers/User-Agent/Firefox"},{"name":"Vary","path":"headers/vary","type":"Headers","url":"/en-US/docs/Web/HTTP/Headers/Vary"},{"name":"Vary (RFC 2616)","path":"rfc2616#section-14.44","type":"Headers","url":"/doc/html/rfc2616#section-14.44"},{"name":"Vary (RFC 7231)","path":"rfc7231#section-7.1.4","type":"Headers","url":"/doc/html/rfc7231#section-7.1.4"},{"name":"Via","path":"headers/via","type":"Headers","url":"/en-US/docs/Web/HTTP/Headers/Via"},{"name":"Via (RFC 2616)","path":"rfc2616#section-14.45","type":"Headers","url":"/doc/html/rfc2616#section-14.45"},{"name":"Viewport-Width","path":"headers/viewport-width","type":"Headers","url":"/en-US/docs/Web/HTTP/Headers/Viewport-Width"},{"name":"Warning","path":"headers/warning","type":"Headers","url":"/en-US/docs/Web/HTTP/Headers/Warning"},{"name":"Warning (RFC 2616)","path":"rfc2616#section-14.46","type":"Headers","url":"/doc/html/rfc2616#section-14.46"},{"name":"Width","path":"headers/width","type":"Headers","url":"/en-US/docs/Web/HTTP/Headers/Width"},{"name":"WWW-Authenticate","path":"headers/www-authenticate","type":"Headers","url":"/en-US/docs/Web/HTTP/Headers/WWW-Authenticate"},{"name":"WWW-Authenticate (RFC 2616)","path":"rfc2616#section-14.47","type":"Headers","url":"/doc/html/rfc2616#section-14.47"},{"name":"X-Content-Type-Options","path":"headers/x-content-type-options","type":"Headers","url":"/en-US/docs/Web/HTTP/Headers/X-Content-Type-Options"},{"name":"X-DNS-Prefetch-Control","path":"headers/x-dns-prefetch-control","type":"Headers","url":"/en-US/docs/Web/HTTP/Headers/X-DNS-Prefetch-Control"},{"name":"X-Forwarded-For","path":"headers/x-forwarded-for","type":"Headers","url":"/en-US/docs/Web/HTTP/Headers/X-Forwarded-For"},{"name":"X-Forwarded-Host","path":"headers/x-forwarded-host","type":"Headers","url":"/en-US/docs/Web/HTTP/Headers/X-Forwarded-Host"},{"name":"X-Forwarded-Proto","path":"headers/x-forwarded-proto","type":"Headers","url":"/en-US/docs/Web/HTTP/Headers/X-Forwarded-Proto"},{"name":"X-Frame-Options","path":"headers/x-frame-options","type":"Headers","url":"/en-US/docs/Web/HTTP/Headers/X-Frame-Options"}],"types":[{"name":"CSP","count":33,"slug":"csp"},{"name":"Guides","count":34,"slug":"guides"},{"name":"Guides: Basics","count":5,"slug":"guides-basics"},{"name":"Headers","count":159,"slug":"headers"},{"name":"Methods","count":21,"slug":"methods"},{"name":"RFC 2616: HTTP/1.1","count":13,"slug":"rfc-2616-http-1-1"},{"name":"RFC 4918: WebDAV","count":1,"slug":"rfc-4918-webdav"},{"name":"RFC 7230: Message Syntax and Routing","count":9,"slug":"rfc-7230-message-syntax-and-routing"},{"name":"RFC 7231: Semantics and Content","count":4,"slug":"rfc-7231-semantics-and-content"},{"name":"Status","count":96,"slug":"status"}]}